{
    "/js/channels-show.js": "/js/channels-show.js?id=ae01d8424951d6502548",
    "/css/home-high.css": "/css/home-high.css?id=a6672bbff3b3f87ee245",
    "/css/home-low.css": "/css/home-low.css?id=821896efe4d101496e19",
    "/css/home-responsive.css": "/css/home-responsive.css?id=a1fc08bb60e11b4e9820",
    "/css/news-high.css": "/css/news-high.css?id=b8f346cb726af357a731",
    "/css/news-low.css": "/css/news-low.css?id=83b9de8c40de286dc99c",
    "/css/news-responsive.css": "/css/news-responsive.css?id=bc38d80b92e0ba6410f1",
    "/css/channels-high.css": "/css/channels-high.css?id=b8f346cb726af357a731",
    "/css/channels-low.css": "/css/channels-low.css?id=d248917da33dad5b060a",
    "/css/channels-responsive.css": "/css/channels-responsive.css?id=4fdadd69824a407187d5",
    "/css/pages.css": "/css/pages.css?id=434a5a16366676f2f1e0",
    "/css/reperfilar-home-high.css": "/css/reperfilar-home-high.css?id=69b0d3c9c69a4cc9217d",
    "/css/reperfilar-home-low.css": "/css/reperfilar-home-low.css?id=56167394ec42c9ffb7ef",
    "/css/reperfilar-home-responsive.css": "/css/reperfilar-home-responsive.css?id=1f36c6b98d5377fc55d1",
    "/css/reperfilar-channels-high.css": "/css/reperfilar-channels-high.css?id=5743c751a5224660f692",
    "/css/reperfilar-channels-low.css": "/css/reperfilar-channels-low.css?id=9796e6d58ca098f3cba6",
    "/css/reperfilar-channels-responsive.css": "/css/reperfilar-channels-responsive.css?id=429cafedcba67a8d0804",
    "/css/reperfilar-news-high.css": "/css/reperfilar-news-high.css?id=69b0d3c9c69a4cc9217d",
    "/css/reperfilar-news-low.css": "/css/reperfilar-news-low.css?id=0531d8fa3462d3668d7a",
    "/css/reperfilar-news-responsive.css": "/css/reperfilar-news-responsive.css?id=9726159b82a6ce5a6aae",
    "/js/mi-perfil.js": "/js/mi-perfil.js?id=35f5df8b3aeee616d4e6",
    "/js/news-show.js": "/js/news-show.js?id=68e8ba6fd71cb1ad8d82",
    "/js/home.js": "/js/home.js?id=32dedfb9d4d1296e0b8d",
    "/js/eplanning.js": "/js/eplanning.js?id=20c09364ddf46a601a2f"
}